cloud_orbit_api/__init__.py
cloud_orbit_api/db_factory.py
cloud_orbit_api/main.py
cloud_orbit_api/models.py
cloud_orbit_api-1.1.23.dist-info/METADATA
cloud_orbit_api-1.1.23.dist-info/WHEEL
cloud_orbit_api-1.1.23.dist-info/RECORD
