Metadata-Version: 2.1
Name: cloud-orbit-api
Version: 1.1.23
Summary: This a demo project
Author: sukruth grandhi
Author-email: sukruthgrandhi@gmail.com
Requires-Python: >=3.9,<4.0
Classifier: Programming Language :: Python :: 3
Classifier: Programming Language :: Python :: 3.9
Classifier: Programming Language :: Python :: 3.10
Classifier: Programming Language :: Python :: 3.11
Classifier: Programming Language :: Python :: 3.12
Requires-Dist: fastapi (>=0.110.1,<0.111.0)
Requires-Dist: uvicorn[standard] (>=0.29.0,<0.30.0)
